{
 "resultCount":50,
 "results": [
{"artworkUrl100":"https://raw.githubusercontent.com/Hmam545/Logo/master/1l.jpeg"},
{"artworkUrl100":"https://raw.githubusercontent.com/Hmam545/Logo/master/2l.jpeg"},
{"artworkUrl100":"https://raw.githubusercontent.com/Hmam545/Logo/master/3l.jpeg"}, 
{"artworkUrl100":"https://raw.githubusercontent.com/Hmam545/Logo/master/4l.jpeg"}, 
{"artworkUrl100":"https://raw.githubusercontent.com/Hmam545/Logo/master/5l.jpeg"}, 
{"artworkUrl100":"https://raw.githubusercontent.com/Hmam545/Logo/master/6l.jpeg"}, 
{"artworkUrl100":"https://raw.githubusercontent.com/Hmam545/Logo/master/7l.jpeg"}, 
{"artworkUrl100":"https://raw.githubusercontent.com/Hmam545/Logo/master/8l.jpeg"}, 
{"artworkUrl100":"https://raw.githubusercontent.com/Hmam545/Logo/master/9l.jpeg"}, 
{"artworkUrl100":"https://raw.githubusercontent.com/Hmam545/Logo/master/10l.jpeg"}, 
{"artworkUrl100":"https://raw.githubusercontent.com/Hmam545/Logo/master/11l.jpeg"}, 
{"artworkUrl100":"https://raw.githubusercontent.com/Hmam545/Logo/master/12l.jpeg"}, 
{"artworkUrl100":"https://raw.githubusercontent.com/Hmam545/Logo/master/13l.jpeg"}, 
{"artworkUrl100":"https://raw.githubusercontent.com/Hmam545/Logo/master/14l.jpeg"}, 
{"artworkUrl100":"https://raw.githubusercontent.com/Hmam545/Logo/master/15l.jpeg"}]
}
